AUTHORS
CONTRIBUTING.rst
HISTORY.rst
LICENSE-APACHE2
LICENSE-MIT
MANIFEST.in
README.rst
setup.cfg
setup.py
docs/Makefile
docs/authors.rst
docs/conf.py
docs/contributing.rst
docs/history.rst
docs/index.rst
docs/installation.rst
docs/make.bat
docs/modules.rst
docs/multiaddr.rst
docs/readme.rst
multiaddr/__init__.py
multiaddr/exceptions.py
multiaddr/multiaddr.py
multiaddr/protocols.py
multiaddr/transforms.py
multiaddr/codecs/__init__.py
multiaddr/codecs/cid.py
multiaddr/codecs/domain.py
multiaddr/codecs/fspath.py
multiaddr/codecs/ip4.py
multiaddr/codecs/ip6.py
multiaddr/codecs/onion.py
multiaddr/codecs/onion3.py
multiaddr/codecs/uint16be.py
multiaddr/codecs/utf8.py
planetmint_multiaddr.egg-info/PKG-INFO
planetmint_multiaddr.egg-info/SOURCES.txt
planetmint_multiaddr.egg-info/dependency_links.txt
planetmint_multiaddr.egg-info/not-zip-safe
planetmint_multiaddr.egg-info/requires.txt
planetmint_multiaddr.egg-info/top_level.txt
tests/__init__.py
tests/test_multiaddr.py
tests/test_protocols.py
tests/test_transforms.py