Metadata-Version: 2.1
Name: planetmint-multiaddr
Version: 0.0.10
Summary: Python implementation of jbenet's multiaddr
Home-page: https://github.com/planetmint/py-multiaddr
Download-URL: https://github.com/multiformats/py-multiaddr/tarball/0.0.10
Author: Steven Buss
Author-email: steven.buss@gmail.com
License: MIT License
Keywords: multiaddr
Classifier: Development Status :: 2 - Pre-Alpha
Classifier: Intended Audience :: Developers
Classifier: License :: OSI Approved :: MIT License
Classifier: Natural Language :: English
Classifier: Programming Language :: Python :: 3 :: Only
Classifier: Programming Language :: Python :: 3.5
Classifier: Programming Language :: Python :: 3.6
Classifier: Programming Language :: Python :: 3.7
Classifier: Programming Language :: Python :: 3.8
Classifier: Programming Language :: Python :: 3.9
Requires-Python: >=3.5
License-File: LICENSE-APACHE2
License-File: LICENSE-MIT
License-File: AUTHORS
